nonebot_plugin_nobahpicture/__init__.py
nonebot_plugin_nobahpicture/config.py
nonebot_plugin_nobahpicture/get_picture.py
nonebot_plugin_nobahpicture/rules.py
nonebot_plugin_nobahpicture-1.0.2.dist-info/LICENSE
nonebot_plugin_nobahpicture-1.0.2.dist-info/METADATA
nonebot_plugin_nobahpicture-1.0.2.dist-info/WHEEL
nonebot_plugin_nobahpicture-1.0.2.dist-info/top_level.txt
nonebot_plugin_nobahpicture-1.0.2.dist-info/RECORD
