Metadata-Version: 2.1
Name: nonebot-plugin-nobahpicture
Version: 1.0.2
Summary: 获取碧蓝档案涩图
Home-page: https://github.com/Lptr-byte/nonebot-plugin-nobahpicture
Author: Hansa
Author-email: hanasakayui2022@gmail.com
License: UNKNOWN
Platform: UNKNOWN
Classifier: Programming Language :: Python :: 3
Classifier: License :: OSI Approved :: MIT License
License-File: LICENSE
Requires-Dist: httpx (==0.24.1)
Requires-Dist: nonebot-adapter-onebot
Requires-Dist: nonebot2 (==2.0.0)
